mcv_walker/__init__.py
mcv_walker/direction.py
mcv_walker/grid.py
mcv_walker/grid_state.py
mcv_walker/main.py
mcv_walker-0.1.8.dist-info/WHEEL
mcv_walker-0.1.8.dist-info/entry_points.txt
mcv_walker-0.1.8.dist-info/METADATA
mcv_walker-0.1.8.dist-info/RECORD
