Metadata-Version: 2.1
Name: mcv-walker
Version: 0.1.8
Summary: 
Author: Greg Olmschenk
Author-email: greg@olmschenk.com
Requires-Python: >=3.8,<4.0
Classifier: Programming Language :: Python :: 3
Classifier: Programming Language :: Python :: 3.8
Classifier: Programming Language :: Python :: 3.9
Classifier: Programming Language :: Python :: 3.10
Classifier: Programming Language :: Python :: 3.11
Requires-Dist: numpy (>=1.23.5,<2.0.0)
Requires-Dist: pynput (>=1.7.6,<2.0.0)
Requires-Dist: rich (>=13.3.1,<14.0.0)
